lrucache_backend/__init__.py
lrucache_backend/backend.py
django_lrucache_backend-4.0.0.dist-info/LICENSE
django_lrucache_backend-4.0.0.dist-info/WHEEL
django_lrucache_backend-4.0.0.dist-info/METADATA
django_lrucache_backend-4.0.0.dist-info/RECORD
