Metadata-Version: 2.1
Name: django-lrucache-backend
Version: 4.0.0
Summary: A smarter local memory cache backend for Django
Home-page: https://github.com/kogan/django-lrucache-backend
License: MIT
Keywords: django,cache,lru
Author: Josh Smeaton
Author-email: josh.smeaton@gmail.com
Requires-Python: >=3.6.4
Classifier: Development Status :: 5 - Production/Stable
Classifier: Framework :: Django
Classifier: Framework :: Django :: 2.2
Classifier: Framework :: Django :: 3.0
Classifier: Intended Audience :: Developers
Classifier: License :: OSI Approved :: MIT License
Classifier: Programming Language :: Python :: 3
Classifier: Programming Language :: Python :: 3.7
Classifier: Programming Language :: Python :: 3.8
Requires-Dist: django (>=2.2)
Project-URL: Repository, https://github.com/kogan/django-lrucache-backend
